climakitaegui/__init__.py
climakitaegui/core/__init__.py
climakitaegui/core/data_interface.py
climakitaegui/core/data_view.py
climakitaegui/explore/__init__.py
climakitaegui/explore/agnostic.py
climakitaegui/explore/amy.py
climakitaegui/explore/threshold_tools.py
climakitaegui/explore/thresholds.py
climakitaegui/explore/timeseries.py
climakitaegui/explore/warming.py
climakitaegui/util/__init__.py
climakitaegui/util/utils.py
climakitaegui-1.3.0.dist-info/licenses/LICENSE
climakitaegui-1.3.0.dist-info/METADATA
climakitaegui-1.3.0.dist-info/WHEEL
climakitaegui-1.3.0.dist-info/top_level.txt
climakitaegui-1.3.0.dist-info/RECORD
