Metadata-Version: 2.4
Name: climakitaegui
Version: 1.3.0
Summary: Climate data analysis toolkit GUI support
Home-page: https://github.com/cal-adapt/climakitaegui
Author: Cal-Adapt Analytics Engine Team
Author-email: analytics@cal-adapt.org
License: BSD 3-Clause License
Classifier: Programming Language :: Python :: 3
Classifier: License :: OSI Approved :: BSD License
Classifier: Operating System :: OS Independent
Classifier: Development Status :: 1 - Planning
License-File: LICENSE
Requires-Dist: climakitae
Requires-Dist: geoviews
Requires-Dist: holoviews
Requires-Dist: hvplot
Requires-Dist: ipython<=8.17.2
Requires-Dist: matplotlib
Requires-Dist: panel<=1.5.5
Provides-Extra: docs
Requires-Dist: Sphinx; extra == "docs"
Requires-Dist: sphinx-book-theme; extra == "docs"
Requires-Dist: sphinx-design; extra == "docs"
Requires-Dist: nbsphinx; extra == "docs"
Dynamic: description
Dynamic: description-content-type
Dynamic: license-file
